[{"title": "рд╡рд┐.рд╕рдВ", "value": "реирежреорем рдЖрд╖рд╛рдв резреи рдордВрдЧрд▓рд╡рд╛рд░"}, {"title": "рдИрд╕рд╡реА", "value": "2029 Jun 26, Tuesday"}, {"title": "рдиреЗрдкрд╛рд▓ рд╕рдВрд╡рдд", "value": "1149 рддрдЫрд▓рд╛рдереНрд╡ рдкреБрдиреНрд╣рд┐-15"}, {"title": "рд╕реВрд░реНрдп", "value": "5:11тШАя╕П, 19:04ЁЯМд"}, {"title": "рдЪрдиреНрджреНрд░", "value": "19:29тШ╜, 5:10тШ╛"}, {"title": "рддрд┐рдерд┐", "value": "рдкреВрд░реНрдгрд┐рдорд╛ upto 9:10:29, рдЙрдкрд░рд╛рдиреНрдд: рдкреНрд░рддрд┐рдкрджрд╛"}, {"title": "рдкрдХреНрд╖", "value": "рдЬреЗрд╖реНрда рд╢реБрдХреНрд▓ рдкрдХреНрд╖ ЁЯМХ"}, {"title": "рдирдХреНрд╖рддреНрд░", "value": "рдореВрд▓ upto 13:58:38, рдЙрдкрд░рд╛рдиреНрдд: рдкреВрд░реНрд╡рд╛рд╖рд╛рдврд╛"}, {"title": "рдпреЛрдЧ", "value": "рд╢реБрдХреНрд▓ upto 7:20:54, рдЙрдкрд░рд╛рдиреНрдд: рдмреНрд░рд╣реНрдо (рд╕рдорд╛рдкреНрддреА)"}, {"title": "рдХрд░рдг", "value": "рдмрд╡ upto 9:10:29"}, {"title": "рдЪрдиреНрджреНрд░ рд░рд╛рд╢рд┐", "value": "рдзрдиреБ тЩР"}, {"title": "рджрд┐рдирдорд╛рди", "value": "34 рдШрдбреА 42 рдкрд▓рд╛ - 13hr 53min"}, {"title": "рдЛрддреБ", "value": "рдЧреНрд░реАрд╖реНрдо-Summer"}, {"title": "рдЖрдпрд╛рди", "value": "рдЙрддреНрддрд░рд╛рдпрдг"}]