[{"title": "рд╡рд┐.рд╕рдВ", "value": "реирежреорем рдЖрд╖рд╛рдв реирез рдмрд┐рд╣реАрд╡рд╛рд░"}, {"title": "рдИрд╕рд╡реА", "value": "2029 Jul 5, Thursday"}, {"title": "рдиреЗрдкрд╛рд▓ рд╕рдВрд╡рдд", "value": "1149 рддрдЫрд▓рд╛рдЧрд╛ рдирд╡рдореА-24"}, {"title": "рд╕реВрд░реНрдп", "value": "5:14тШАя╕П, 19:04ЁЯМд"}, {"title": "рдЪрдиреНрджреНрд░", "value": "0:05тШ╜, 13:32тШ╛"}, {"title": "рддрд┐рдерд┐", "value": "рдирд╡рдореА upto 15:13:40, рдЙрдкрд░рд╛рдиреНрдд: рджрд╢рдореА"}, {"title": "рдкрдХреНрд╖", "value": "рдЖрд╖рд╛рдв рдХреГрд╖реНрдг рдкрдХреНрд╖ ЁЯМЧ"}, {"title": "рдирдХреНрд╖рддреНрд░", "value": "рдЕрд╢реНрд╡рд┐рдиреА upto 27:13:33, рдЙрдкрд░рд╛рдиреНрдд: рднрд░рдгреА"}, {"title": "рдпреЛрдЧ", "value": "рд╕реБрдХрд░реНрдорд╛ upto 27:29:16, рдЙрдкрд░рд╛рдиреНрдд: рдзреГрддрд┐"}, {"title": "рдХрд░рдг", "value": "рдЧрд░ upto 15:13:40"}, {"title": "рдЪрдиреНрджреНрд░ рд░рд╛рд╢рд┐", "value": "рдореЗрд╖ тЩИ"}, {"title": "рджрд┐рдирдорд╛рди", "value": "34 рдШрдбреА 35 рдкрд▓рд╛ - 13hr 50min"}, {"title": "рдЛрддреБ", "value": "рдЧреНрд░реАрд╖реНрдо-Summer"}, {"title": "рдЖрдпрд╛рди", "value": "рдЙрддреНрддрд░рд╛рдпрдг"}]