[{"title": "рд╡рд┐.рд╕рдВ", "value": "реирежрепреж рдЖрд╖рд╛рдв реирел рд╢рдирд┐рд╡рд╛рд░"}, {"title": "рдИрд╕рд╡реА", "value": "2033 Jul 9, Saturday"}, {"title": "рдиреЗрдкрд╛рд▓ рд╕рдВрд╡рдд", "value": "1153 рджрд┐рд▓реНрд▓рд╛рдереНрд╡ рджреНрд╡рд╛рджрд╢реА-12"}, {"title": "рд╕реВрд░реНрдп", "value": "5:15тШАя╕П, 19:04ЁЯМд"}, {"title": "рдЪрдиреНрджреНрд░", "value": "16:11тШ╜, 2:27тШ╛"}, {"title": "рддрд┐рдерд┐", "value": "рджреНрд╡рд╛рджрд╢реА upto 17:52:57, рдЙрдкрд░рд╛рдиреНрдд: рддреНрд░рдпреЛрджрд╢реА"}, {"title": "рдкрдХреНрд╖", "value": "рдЖрд╖рд╛рдв рд╢реБрдХреНрд▓ рдкрдХреНрд╖ ЁЯМФ"}, {"title": "рдирдХреНрд╖рддреНрд░", "value": "рдЕрдиреБрд░рд╛рдзрд╛ upto 16:44:1, рдЙрдкрд░рд╛рдиреНрдд: рдЬреНрдпреЗрд╖реНрдард╛"}, {"title": "рдпреЛрдЧ", "value": "рд╢реБрдн upto 11:7:28, рдЙрдкрд░рд╛рдиреНрдд: рд╢реБрдХреНрд▓"}, {"title": "рдХрд░рдг", "value": "рдмрд╡ upto 5:50:1, рдЙрдкрд░рд╛рдиреНрдд: рдмрд╛рд▓рд╡ upto 17:52:57"}, {"title": "рдЪрдиреНрджреНрд░ рд░рд╛рд╢рд┐", "value": "рд╡реГрд╢реНрдЪрд┐рдХ тЩП"}, {"title": "рджрд┐рдирдорд╛рди", "value": "34 рдШрдбреА 32 рдкрд▓рд╛ - 13hr 49min"}, {"title": "рдЛрддреБ", "value": "рдЧреНрд░реАрд╖реНрдо-Summer"}, {"title": "рдЖрдпрд╛рди", "value": "рдЙрддреНрддрд░рд╛рдпрдг"}]