[{"title": "рд╡рд┐.рд╕рдВ", "value": "реирежреорел рдЕрд╕реЛрдЬ резрел рд╢рдирд┐рд╡рд╛рд░"}, {"title": "рдИрд╕рд╡реА", "value": "2028 Sep 30, Saturday"}, {"title": "рдиреЗрдкрд╛рд▓ рд╕рдВрд╡рдд", "value": "1148 рдХреМрд▓рд╛рдереНрд╡ рджреНрд╡рд╛рджрд╢реА-12"}, {"title": "рд╕реВрд░реНрдп", "value": "5:57тШАя╕П, 17:51ЁЯМд"}, {"title": "рдЪрдиреНрджреНрд░", "value": "15:55тШ╜, 2:53тШ╛"}, {"title": "рддрд┐рдерд┐", "value": "рджреНрд╡рд╛рджрд╢реА upto 14:50:51, рдЙрдкрд░рд╛рдиреНрдд: рддреНрд░рдпреЛрджрд╢реА"}, {"title": "рдкрдХреНрд╖", "value": "рдЕрд╕реЛрдЬ рд╢реБрдХреНрд▓ рдкрдХреНрд╖ ЁЯМФ"}, {"title": "рдирдХреНрд╖рддреНрд░", "value": "рдзрдирд┐рд╖реНрдард╛ upto 13:12:21, рдЙрдкрд░рд╛рдиреНрдд: рд╢рддрднрд┐рд╖рд╛"}, {"title": "рдпреЛрдЧ", "value": "рдзреГрддрд┐ upto 6:49:38, рдЙрдкрд░рд╛рдиреНрдд: рд╢реВрд▓"}, {"title": "рдХрд░рдг", "value": "рдмрд╛рд▓рд╡ upto 14:50:51"}, {"title": "рдЪрдиреНрджреНрд░ рд░рд╛рд╢рд┐", "value": "рдХреБрдореНрдн тЩТ"}, {"title": "рджрд┐рдирдорд╛рди", "value": "29 рдШрдбреА 45 рдкрд▓рд╛ - 11hr 54min"}, {"title": "рдЛрддреБ", "value": "рд╢рд░рджреН-Autumn"}, {"title": "рдЖрдпрд╛рди", "value": "рджрдХреНрд╖рд┐рдгрд╛рдпрди"}]