[{"title": "рд╡рд┐.рд╕рдВ", "value": "реирежреореи рдХрд╛рд░реНрддрд┐рдХ рем рдмреБрдзрд╡рд╛рд░"}, {"title": "рдИрд╕рд╡реА", "value": "2025 Oct 22, Wednesday"}, {"title": "рдиреЗрдкрд╛рд▓ рд╕рдВрд╡рдд", "value": "1146 рдХрдЫрд▓рд╛рдереНрд╡ рдкрд╛рд░реБ-1"}, {"title": "рд╕реВрд░реНрдп", "value": "6:09тШАя╕П, 17:29ЁЯМд"}, {"title": "рдЪрдиреНрджреНрд░", "value": "6:46тШ╜, 17:46тШ╛"}, {"title": "рддрд┐рдерд┐", "value": "рдкреНрд░рддрд┐рдкрджрд╛ upto 20:34:11, рдЙрдкрд░рд╛рдиреНрдд: рджреНрд╡рд┐рддреАрдпрд╛"}, {"title": "рдкрдХреНрд╖", "value": "рдХрд╛рд░реНрддрд┐рдХ рд╢реБрдХреНрд▓ рдкрдХреНрд╖ ЁЯМТ"}, {"title": "рдирдХреНрд╖рддреНрд░", "value": "рд╕реНрд╡рд╛рддреА upto 26:8:19, рдЙрдкрд░рд╛рдиреНрдд: рд╡рд┐рд╢рд╛рдЦрд╛"}, {"title": "рдпреЛрдЧ", "value": "рдкреНрд░реАрддрд┐ upto 28:21:52, рдЙрдкрд░рд╛рдиреНрдд: рдЖрдпреБрд╖реНрдорд╛рди"}, {"title": "рдХрд░рдг", "value": "рдХрд┐рдиреНрд╕реНрддреБрдШреНрдирд╛ upto 7:21:18, рдЙрдкрд░рд╛рдиреНрдд: рдмрд╡ upto 20:34:11"}, {"title": "рдЪрдиреНрджреНрд░ рд░рд╛рд╢рд┐", "value": "рддреБрд▓рд╛ тЩО"}, {"title": "рджрд┐рдирдорд╛рди", "value": "28 рдШрдбреА 20 рдкрд▓рд╛ - 11hr 20min"}, {"title": "рдЛрддреБ", "value": "рд╢рд░рджреН-Autumn"}, {"title": "рдЖрдпрд╛рди", "value": "рджрдХреНрд╖рд┐рдгрд╛рдпрди"}]