[{"title": "рд╡рд┐.рд╕рдВ", "value": "реирежреореи рдЖрд╖рд╛рдв резрен рдордВрдЧрд▓рд╡рд╛рд░"}, {"title": "рдИрд╕рд╡реА", "value": "2025 Jul 1, Tuesday"}, {"title": "рдиреЗрдкрд╛рд▓ рд╕рдВрд╡рдд", "value": "1145 рджрд┐рд▓реНрд▓рд╛рдереНрд╡ рд╖рд╖реНрдареА-6"}, {"title": "рд╕реВрд░реНрдп", "value": "5:12тШАя╕П, 19:04ЁЯМд"}, {"title": "рдЪрдиреНрджреНрд░", "value": "10:49тШ╜, 23:18тШ╛"}, {"title": "рддрд┐рдерд┐", "value": "рд╖рд╖реНрдареА upto 10:40:11, рдЙрдкрд░рд╛рдиреНрдд: рд╕рдкреНрддрдореА"}, {"title": "рдкрдХреНрд╖", "value": "рдЖрд╖рд╛рдв рд╢реБрдХреНрд▓ рдкрдХреНрд╖ ЁЯМУ"}, {"title": "рдирдХреНрд╖рддреНрд░", "value": "рдкреВрд░реНрд╡рдлрд╛рд▓реНрдЧреБрдиреА upto 9:12:9, рдЙрдкрд░рд╛рдиреНрдд: рдЙрддреНрддрд░рдлрд╛рд▓реНрдЧреБрдиреА"}, {"title": "рдпреЛрдЧ", "value": "рд╡реНрдпрддреАрдкрд╛рдд upto 17:38:26, рдЙрдкрд░рд╛рдиреНрдд: рд╡рд░рд┐рдпрд╛рди"}, {"title": "рдХрд░рдг", "value": "рддреИрддрд┐рд▓ upto 10:40:11"}, {"title": "рдЪрдиреНрджреНрд░ рд░рд╛рд╢рд┐", "value": "рд╕рд┐рдВрд╣ тЩМ upto 15:43:57, рдЙрдкрд░рд╛рдиреНрдд: рдХрдиреНрдпрд╛ тЩН"}, {"title": "рджрд┐рдирдорд╛рди", "value": "34 рдШрдбреА 40 рдкрд▓рд╛ - 13hr 52min"}, {"title": "рдЛрддреБ", "value": "рдЧреНрд░реАрд╖реНрдо-Summer"}, {"title": "рдЖрдпрд╛рди", "value": "рдЙрддреНрддрд░рд╛рдпрдг"}]