[{"title": "рд╡рд┐.рд╕рдВ", "value": "реирежреореп рдлрд╛рдЧреБрди реирео рд╢рдирд┐рд╡рд╛рд░"}, {"title": "рдИрд╕рд╡реА", "value": "2033 Mar 12, Saturday"}, {"title": "рдиреЗрдкрд╛рд▓ рд╕рдВрд╡рдд", "value": "1153 рдЪрд┐рд▓реНрд▓рд╛рдереНрд╡ рджреНрд╡рд╛рджрд╢реА-12"}, {"title": "рд╕реВрд░реНрдп", "value": "6:18тШАя╕П, 18:11ЁЯМд"}, {"title": "рдЪрдиреНрджреНрд░", "value": "15:11тШ╜, 3:45тШ╛"}, {"title": "рддрд┐рдерд┐", "value": "рджреНрд╡рд╛рджрд╢реА upto 24:4:31, рдЙрдкрд░рд╛рдиреНрдд: рддреНрд░рдпреЛрджрд╢реА"}, {"title": "рдкрдХреНрд╖", "value": "рдлрд╛рдЧреБрди рд╢реБрдХреНрд▓ рдкрдХреНрд╖ ЁЯМФ"}, {"title": "рдирдХреНрд╖рддреНрд░", "value": "рддрд┐рд╖реНрдп upto 13:7:29, рдЙрдкрд░рд╛рдиреНрдд: рдЕрд╢реНрд▓реЗрд╖рд╛"}, {"title": "рдпреЛрдЧ", "value": "рдЕрддрд┐рдЧрдВрдб upto 23:27:18, рдЙрдкрд░рд╛рдиреНрдд: рд╕реБрдХрд░реНрдорд╛"}, {"title": "рдХрд░рдг", "value": "рдмрд╡ upto 11:3:24, рдЙрдкрд░рд╛рдиреНрдд: рдмрд╛рд▓рд╡ upto 24:4:31"}, {"title": "рдЪрдиреНрджреНрд░ рд░рд╛рд╢рд┐", "value": "рдХрд░реНрдХрдЯ тЩЛ"}, {"title": "рджрд┐рдирдорд╛рди", "value": "29 рдШрдбреА 42 рдкрд▓рд╛ - 11hr 53min"}, {"title": "рдЛрддреБ", "value": "рд╢рд┐рд╢рд┐рд░-Winter"}, {"title": "рдЖрдпрд╛рди", "value": "рдЙрддреНрддрд░рд╛рдпрдг"}]