[{"title": "рд╡рд┐.рд╕рдВ", "value": "реирежреореж рдЕрд╕реЛрдЬ рем рд╢рдирд┐рд╡рд╛рд░"}, {"title": "рдИрд╕рд╡реА", "value": "2023 Sep 23, Saturday"}, {"title": "рдиреЗрдкрд╛рд▓ рд╕рдВрд╡рдд", "value": "1143 рдЮрд▓рд╛рдереНрд╡ рдЕрд╖реНрдЯрдореА-8"}, {"title": "рд╕реВрд░реНрдп", "value": "5:53тШАя╕П, 18:00ЁЯМд"}, {"title": "рдЪрдиреНрджреНрд░", "value": "13:41тШ╜, 23:56тШ╛"}, {"title": "рддрд┐рдерд┐", "value": "рдЕрд╖реНрдЯрдореА upto 12:30:7, рдЙрдкрд░рд╛рдиреНрдд: рдирд╡рдореА"}, {"title": "рдкрдХреНрд╖", "value": "рднрд╛рджреНрд░ рд╢реБрдХреНрд▓ рдкрдХреНрд╖ ЁЯМУ"}, {"title": "рдирдХреНрд╖рддреНрд░", "value": "рдореВрд▓ upto 15:8:3, рдЙрдкрд░рд╛рдиреНрдд: рдкреВрд░реНрд╡рд╛рд╖рд╛рдврд╛"}, {"title": "рдпреЛрдЧ", "value": "рд╕реМрднрд╛рдЧреНрдп upto 21:42:57, рдЙрдкрд░рд╛рдиреНрдд: рд╢реЛрднрди"}, {"title": "рдХрд░рдг", "value": "рдмрд╡ upto 12:30:7"}, {"title": "рдЪрдиреНрджреНрд░ рд░рд╛рд╢рд┐", "value": "рдзрдиреБ тЩР"}, {"title": "рджрд┐рдирдорд╛рди", "value": "30 рдШрдбреА 17 рдкрд▓рд╛ - 12hr 7min"}, {"title": "рдЛрддреБ", "value": "рд╢рд░рджреН-Autumn"}, {"title": "рдЖрдпрд╛рди", "value": "рджрдХреНрд╖рд┐рдгрд╛рдпрди"}]