[{"title": "рд╡рд┐.рд╕рдВ", "value": "реирежреорео рднрд╛рджреНрд░ рек рдмрд┐рд╣реАрд╡рд╛рд░"}, {"title": "рдИрд╕рд╡реА", "value": "2031 Aug 21, Thursday"}, {"title": "рдиреЗрдкрд╛рд▓ рд╕рдВрд╡рдд", "value": "1151 рдЕрдирд╛рд▓рд╛рдереНрд╡ рддреГрддреАрдпрд╛-3"}, {"title": "рд╕реВрд░реНрдп", "value": "5:38тШАя╕П, 18:37ЁЯМд"}, {"title": "рдЪрдиреНрджреНрд░", "value": "8:11тШ╜, 20:13тШ╛"}, {"title": "рддрд┐рдерд┐", "value": "рддреГрддреАрдпрд╛ upto 13:55:10, рдЙрдкрд░рд╛рдиреНрдд: рдЪрддреБрд░реНрдереА"}, {"title": "рдкрдХреНрд╖", "value": "рдЕрдзрд┐рдХ рднрд╛рджреНрд░ рд╢реБрдХреНрд▓ рдкрдХреНрд╖ ЁЯМТ"}, {"title": "рдирдХреНрд╖рддреНрд░", "value": "рдЙрддреНрддрд░рдлрд╛рд▓реНрдЧреБрдиреА upto 14:17:19, рдЙрдкрд░рд╛рдиреНрдд: рд╣рд╕реНрдд"}, {"title": "рдпреЛрдЧ", "value": "рд╕рд┐рджреНрдз upto 7:33:48, рдЙрдкрд░рд╛рдиреНрдд: рд╕рд╛рдШреНрдп"}, {"title": "рдХрд░рдг", "value": "рдЧрд░ upto 13:55:10"}, {"title": "рдЪрдиреНрджреНрд░ рд░рд╛рд╢рд┐", "value": "рдХрдиреНрдпрд╛ тЩН"}, {"title": "рджрд┐рдирдорд╛рди", "value": "32 рдШрдбреА 27 рдкрд▓рд╛ - 12hr 59min"}, {"title": "рдЛрддреБ", "value": "рд╡рд░реНрд╖рд╛-Monsoon"}, {"title": "рдЖрдпрд╛рди", "value": "рджрдХреНрд╖рд┐рдгрд╛рдпрди"}]