[{"title": "рд╡рд┐.рд╕рдВ", "value": "реирежреорек рдЬреЗрд╖реНрда реп рдЖрдЗрддрд╡рд╛рд░"}, {"title": "рдИрд╕рд╡реА", "value": "2027 May 23, Sunday"}, {"title": "рдиреЗрдкрд╛рд▓ рд╕рдВрд╡рдд", "value": "1147 рд╡рдЫрд▓рд╛рдЧрд╛ рддреГрддреАрдпрд╛-18"}, {"title": "рд╕реВрд░реНрдп", "value": "5:12тШАя╕П, 18:51ЁЯМд"}, {"title": "рдЪрдиреНрджреНрд░", "value": "21:44тШ╜, 7:10тШ╛"}, {"title": "рддрд┐рдерд┐", "value": "рддреГрддреАрдпрд╛ upto 21:0:42, рдЙрдкрд░рд╛рдиреНрдд: рдЪрддреБрд░реНрдереА"}, {"title": "рдкрдХреНрд╖", "value": "рдЬреЗрд╖реНрда рдХреГрд╖реНрдг рдкрдХреНрд╖ ЁЯМЦ"}, {"title": "рдирдХреНрд╖рддреНрд░", "value": "рдореВрд▓ upto 19:35:54, рдЙрдкрд░рд╛рдиреНрдд: рдкреВрд░реНрд╡рд╛рд╖рд╛рдврд╛"}, {"title": "рдпреЛрдЧ", "value": "рд╕рд╛рдШреНрдп upto 23:19:35, рдЙрдкрд░рд╛рдиреНрдд: рд╢реБрдн"}, {"title": "рдХрд░рдг", "value": "рд╡рдгрд┐рдЬ upto 7:59:4, рдЙрдкрд░рд╛рдиреНрдд: рд╡рд┐рд╖реНрдЯрд┐ upto 21:0:42"}, {"title": "рдЪрдиреНрджреНрд░ рд░рд╛рд╢рд┐", "value": "рдзрдиреБ тЩР"}, {"title": "рджрд┐рдирдорд╛рди", "value": "34 рдШрдбреА 7 рдкрд▓рд╛ - 13hr 39min"}, {"title": "рдЛрддреБ", "value": "рдЧреНрд░реАрд╖реНрдо-Summer"}, {"title": "рдЖрдпрд╛рди", "value": "рдЙрддреНрддрд░рд╛рдпрдг"}]