[{"title": "рд╡рд┐.рд╕рдВ", "value": "реирежреореж рдлрд╛рдЧреБрди реирез рд╕реЛрдордмрд╛рд░"}, {"title": "рдИрд╕рд╡реА", "value": "2024 Mar 4, Monday"}, {"title": "рдиреЗрдкрд╛рд▓ рд╕рдВрд╡рдд", "value": "1144 рд╕рд┐рд▓реНрд▓рд╛рдЧрд╛ рдЕрд╖реНрдЯрдореА-23"}, {"title": "рд╕реВрд░реНрдп", "value": "6:25тШАя╕П, 18:07ЁЯМд"}, {"title": "рдЪрдиреНрджреНрд░", "value": "1:25тШ╜, 11:39тШ╛"}, {"title": "рддрд┐рдерд┐", "value": "рдЕрд╖реНрдЯрдореА upto 9:2:35, рдЙрдкрд░рд╛рдиреНрдд: рдирд╡рдореА"}, {"title": "рдкрдХреНрд╖", "value": "рдлрд╛рдЧреБрди рдХреГрд╖реНрдг рдкрдХреНрд╖ ЁЯМЧ"}, {"title": "рдирдХреНрд╖рддреНрд░", "value": "рдЬреНрдпреЗрд╖реНрдард╛ upto 16:31:53, рдЙрдкрд░рд╛рдиреНрдд: рдореВрд▓"}, {"title": "рдпреЛрдЧ", "value": "рд╡рдЬреНрд░ upto 16:16:36, рдЙрдкрд░рд╛рдиреНрдд: рд╕рд┐рджреНрдзрд┐"}, {"title": "рдХрд░рдг", "value": "рдХреМрд▓рд╡ upto 9:2:35"}, {"title": "рдЪрдиреНрджреНрд░ рд░рд╛рд╢рд┐", "value": "рд╡реГрд╢реНрдЪрд┐рдХ тЩП upto 16:31:53, рдЙрдкрд░рд╛рдиреНрдд: рдзрдиреБ тЩР"}, {"title": "рджрд┐рдирдорд╛рди", "value": "29 рдШрдбреА 15 рдкрд▓рд╛ - 11hr 42min"}, {"title": "рдЛрддреБ", "value": "рд╢рд┐рд╢рд┐рд░-Winter"}, {"title": "рдЖрдпрд╛рди", "value": "рдЙрддреНрддрд░рд╛рдпрдг"}]