[{"title": "рд╡рд┐.рд╕рдВ", "value": "реирежреорео рдлрд╛рдЧреБрди резреж рд╕реЛрдордмрд╛рд░"}, {"title": "рдИрд╕рд╡реА", "value": "2032 Feb 23, Monday"}, {"title": "рдиреЗрдкрд╛рд▓ рд╕рдВрд╡рдд", "value": "1152 рд╕рд┐рд▓реНрд▓рд╛рдереНрд╡ рддреНрд░рдпреЛрджрд╢реА-13"}, {"title": "рд╕реВрд░реНрдп", "value": "6:35тШАя╕П, 18:01ЁЯМд"}, {"title": "рдЪрдиреНрджреНрд░", "value": "15:37тШ╜, 4:21тШ╛"}, {"title": "рддрд┐рдерд┐", "value": "рддреНрд░рдпреЛрджрд╢реА upto 32:45:57 (Full Night)"}, {"title": "рдкрдХреНрд╖", "value": "рдорд╛рдШ рд╢реБрдХреНрд▓ рдкрдХреНрд╖ ЁЯМФ"}, {"title": "рдирдХреНрд╖рддреНрд░", "value": "рддрд┐рд╖реНрдп upto 32:36:9 (Full Night)"}, {"title": "рдпреЛрдЧ", "value": "рд╕реМрднрд╛рдЧреНрдп upto 24:59:39, рдЙрдкрд░рд╛рдиреНрдд: рд╢реЛрднрди"}, {"title": "рдХрд░рдг", "value": "рддреИрддрд┐рд▓ upto 32:45:57"}, {"title": "рдЪрдиреНрджреНрд░ рд░рд╛рд╢рд┐", "value": "рдХрд░реНрдХрдЯ тЩЛ"}, {"title": "рджрд┐рдирдорд╛рди", "value": "28 рдШрдбреА 35 рдкрд▓рд╛ - 11hr 26min"}, {"title": "рдЛрддреБ", "value": "рд╢рд┐рд╢рд┐рд░-Winter"}, {"title": "рдЖрдпрд╛рди", "value": "рдЙрддреНрддрд░рд╛рдпрдг"}]