[{"title": "рд╡рд┐.рд╕рдВ", "value": "реирежреореп рдХрд╛рд░реНрддрд┐рдХ рейреж рд╕реЛрдордмрд╛рд░"}, {"title": "рдИрд╕рд╡реА", "value": "2032 Nov 15, Monday"}, {"title": "рдиреЗрдкрд╛рд▓ рд╕рдВрд╡рдд", "value": "1153 рдХрдЫрд▓рд╛рдереНрд╡ рддреНрд░рдпреЛрджрд╢реА-13"}, {"title": "рд╕реВрд░реНрдп", "value": "6:26тШАя╕П, 17:12ЁЯМд"}, {"title": "рдЪрдиреНрджреНрд░", "value": "15:55тШ╜, 4:15тШ╛"}, {"title": "рддрд┐рдерд┐", "value": "рддреНрд░рдпреЛрджрд╢реА upto 16:30:33, рдЙрдкрд░рд╛рдиреНрдд: рдЪрддреБрд░реНрджрд╢реА"}, {"title": "рдкрдХреНрд╖", "value": "рдХрд╛рд░реНрддрд┐рдХ рд╢реБрдХреНрд▓ рдкрдХреНрд╖ ЁЯМФ"}, {"title": "рдирдХреНрд╖рддреНрд░", "value": "рд░реЗрд╡рддреА upto 7:34:21, рдЙрдкрд░рд╛рдиреНрдд: рдЕрд╢реНрд╡рд┐рдиреА"}, {"title": "рдпреЛрдЧ", "value": "рд╕рд┐рджреНрдзрд┐ upto 14:29:47, рдЙрдкрд░рд╛рдиреНрдд: рд╡реНрдпрддреАрдкрд╛рдд"}, {"title": "рдХрд░рдг", "value": "рддреИрддрд┐рд▓ upto 16:30:33"}, {"title": "рдЪрдиреНрджреНрд░ рд░рд╛рд╢рд┐", "value": "рдореАрди тЩУ upto 7:34:21, рдЙрдкрд░рд╛рдиреНрдд: рдореЗрд╖ тЩИ"}, {"title": "рджрд┐рдирдорд╛рди", "value": "26 рдШрдбреА 55 рдкрд▓рд╛ - 10hr 46min"}, {"title": "рдЛрддреБ", "value": "рд╢рд░рджреН-Autumn"}, {"title": "рдЖрдпрд╛рди", "value": "рджрдХреНрд╖рд┐рдгрд╛рдпрди"}]