[{"title": "рд╡рд┐.рд╕рдВ", "value": "реирежрепреж рдЬреЗрд╖реНрда резрек рд╢реБрдХреНрд░рд╡рд╛рд░"}, {"title": "рдИрд╕рд╡реА", "value": "2033 May 27, Friday"}, {"title": "рдиреЗрдкрд╛рд▓ рд╕рдВрд╡рдд", "value": "1153 рд╡рдЫрд▓рд╛рдЧрд╛ рдЪрддреБрд░реНрджрд╢реА-29"}, {"title": "рд╕реВрд░реНрдп", "value": "5:10тШАя╕П, 18:53ЁЯМд"}, {"title": "рдЪрдиреНрджреНрд░", "value": "4:15тШ╜, 17:53тШ╛"}, {"title": "рддрд┐рдерд┐", "value": "рдЪрддреБрд░реНрджрд╢реА upto 19:49:31, рдЙрдкрд░рд╛рдиреНрдд: рдФрдВрд╕реА"}, {"title": "рдкрдХреНрд╖", "value": "рдЬреЗрд╖реНрда рдХреГрд╖реНрдг рдкрдХреНрд╖ ЁЯМС"}, {"title": "рдирдХреНрд╖рддреНрд░", "value": "рднрд░рдгреА upto 13:48:5, рдЙрдкрд░рд╛рдиреНрдд: рдХреГрддреНрддрд┐рдХрд╛"}, {"title": "рдпреЛрдЧ", "value": "рд╢реЛрднрди upto 10:36:52, рдЙрдкрд░рд╛рдиреНрдд: рдЕрддрд┐рдЧрдВрдб"}, {"title": "рдХрд░рдг", "value": "рд╡рд┐рд╖реНрдЯрд┐(рднрджреНрд░рд╛) upto 9:6:29, рдЙрдкрд░рд╛рдиреНрдд: рд╢рдХреБрди upto 19:49:31"}, {"title": "рдЪрдиреНрджреНрд░ рд░рд╛рд╢рд┐", "value": "рдореЗрд╖ тЩИ upto 19:21:30, рдЙрдкрд░рд╛рдиреНрдд: рд╡реГрд╖ тЩЙ"}, {"title": "рджрд┐рдирдорд╛рди", "value": "34 рдШрдбреА 17 рдкрд▓рд╛ - 13hr 43min"}, {"title": "рдЛрддреБ", "value": "рдЧреНрд░реАрд╖реНрдо-Summer"}, {"title": "рдЖрдпрд╛рди", "value": "рдЙрддреНрддрд░рд╛рдпрдг"}]