[{"title": "рд╡рд┐.рд╕рдВ", "value": "реирежреорек рдЕрд╕реЛрдЬ резрей рдмреБрдзрд╡рд╛рд░"}, {"title": "рдИрд╕рд╡реА", "value": "2027 Sep 29, Wednesday"}, {"title": "рдиреЗрдкрд╛рд▓ рд╕рдВрд╡рдд", "value": "1147 рдЮрд▓рд╛рдЧрд╛ рдЪрддреБрд░реНрджрд╢реА-29"}, {"title": "рд╕реВрд░реНрдп", "value": "5:56тШАя╕П, 17:53ЁЯМд"}, {"title": "рдЪрдиреНрджреНрд░", "value": "4:58тШ╜, 17:16тШ╛"}, {"title": "рддрд┐рдерд┐", "value": "рдЪрддреБрд░реНрджрд╢реА upto 11:13:8, рдЙрдкрд░рд╛рдиреНрдд: рдФрдВрд╕реА"}, {"title": "рдкрдХреНрд╖", "value": "рдЕрд╕реЛрдЬ рдХреГрд╖реНрдг рдкрдХреНрд╖ ЁЯМС"}, {"title": "рдирдХреНрд╖рддреНрд░", "value": "рдкреВрд░реНрд╡рдлрд╛рд▓реНрдЧреБрдиреА upto 6:22:43, рдЙрдкрд░рд╛рдиреНрдд:рдЙрддреНрддрд░рдлрд╛рд▓реНрдЧреБрдиреА (рд╕рдорд╛рдкреНрддреА)"}, {"title": "рдпреЛрдЧ", "value": "рд╢реБрдХреНрд▓ upto 24:43:22, рдЙрдкрд░рд╛рдиреНрдд: рдмреНрд░рд╣реНрдо"}, {"title": "рдХрд░рдг", "value": "рд╢рдХреБрди upto 11:13:8"}, {"title": "рдЪрдиреНрджреНрд░ рд░рд╛рд╢рд┐", "value": "рд╕рд┐рдВрд╣ тЩМ upto 11:51:15, рдЙрдкрд░рд╛рдиреНрдд: рдХрдиреНрдпрд╛ тЩН"}, {"title": "рджрд┐рдирдорд╛рди", "value": "29 рдШрдбреА 52 рдкрд▓рд╛ - 11hr 57min"}, {"title": "рдЛрддреБ", "value": "рд╢рд░рджреН-Autumn"}, {"title": "рдЖрдпрд╛рди", "value": "рджрдХреНрд╖рд┐рдгрд╛рдпрди"}]