[{"title": "рд╡рд┐.рд╕рдВ", "value": "реирежреорек рдЕрд╕реЛрдЬ реи рд╢рдирд┐рд╡рд╛рд░"}, {"title": "рдИрд╕рд╡реА", "value": "2027 Sep 18, Saturday"}, {"title": "рдиреЗрдкрд╛рд▓ рд╕рдВрд╡рдд", "value": "1147 рдЮрд▓рд╛рдЧрд╛ рджреНрд╡рд┐рддреАрдпрд╛-17"}, {"title": "рд╕реВрд░реНрдп", "value": "5:51тШАя╕П, 18:06ЁЯМд"}, {"title": "рдЪрдиреНрджреНрд░", "value": "19:05тШ╜, 7:42тШ╛"}, {"title": "рддрд┐рдерд┐", "value": "рджреНрд╡рд┐рддреАрдпрд╛ upto 6:59:44, рдЙрдкрд░рд╛рдиреНрдд: рддреГрддреАрдпрд╛"}, {"title": "рдкрдХреНрд╖", "value": "рдЕрд╕реЛрдЬ рдХреГрд╖реНрдг рдкрдХреНрд╖ ЁЯМЦ"}, {"title": "рдирдХреНрд╖рддреНрд░", "value": "рд░реЗрд╡рддреА upto 17:0:50, рдЙрдкрд░рд╛рдиреНрдд: рдЕрд╢реНрд╡рд┐рдиреА"}, {"title": "рдпреЛрдЧ", "value": "рд╡реГрджреНрдзрд┐ upto 9:17:41, рдЙрдкрд░рд╛рдиреНрдд: рдШреНрд░реБрд╡"}, {"title": "рдХрд░рдг", "value": "рдЧрд░ upto 6:59:44"}, {"title": "рдЪрдиреНрджреНрд░ рд░рд╛рд╢рд┐", "value": "рдореАрди тЩУ upto 17:0:50, рдЙрдкрд░рд╛рдиреНрдд: рдореЗрд╖ тЩИ"}, {"title": "рджрд┐рдирдорд╛рди", "value": "30 рдШрдбреА 37 рдкрд▓рд╛ - 12hr 15min"}, {"title": "рдЛрддреБ", "value": "рд╢рд░рджреН-Autumn"}, {"title": "рдЖрдпрд╛рди", "value": "рджрдХреНрд╖рд┐рдгрд╛рдпрди"}]