[{"title": "рд╡рд┐.рд╕рдВ", "value": "реирежреорем рд╢реНрд░рд╛рд╡рди рейреи рдмрд┐рд╣реАрд╡рд╛рд░"}, {"title": "рдИрд╕рд╡реА", "value": "2029 Aug 16, Thursday"}, {"title": "рдиреЗрдкрд╛рд▓ рд╕рдВрд╡рдд", "value": "1149 рдЧреБрд▓рд╛рдереНрд╡ рд╕рдкреНрддрдореА-7"}, {"title": "рд╕реВрд░реНрдп", "value": "5:35тШАя╕П, 18:42ЁЯМд"}, {"title": "рдЪрдиреНрджреНрд░", "value": "11:58тШ╜, 22:49тШ╛"}, {"title": "рддрд┐рдерд┐", "value": "рд╕рдкреНрддрдореА upto 13:46:49, рдЙрдкрд░рд╛рдиреНрдд: рдЕрд╖реНрдЯрдореА"}, {"title": "рдкрдХреНрд╖", "value": "рд╢реНрд░рд╛рд╡рди рд╢реБрдХреНрд▓ рдкрдХреНрд╖ ЁЯМУ"}, {"title": "рдирдХреНрд╖рддреНрд░", "value": "рд╕реНрд╡рд╛рддреА upto 7:51:50, рдЙрдкрд░рд╛рдиреНрдд: рд╡рд┐рд╢рд╛рдЦрд╛"}, {"title": "рдпреЛрдЧ", "value": "рд╢реБрдХреНрд▓ upto 9:4:2, рдЙрдкрд░рд╛рдиреНрдд: рдмреНрд░рд╣реНрдо"}, {"title": "рдХрд░рдг", "value": "рд╡рдгрд┐рдЬ upto 13:46:49"}, {"title": "рдЪрдиреНрджреНрд░ рд░рд╛рд╢рд┐", "value": "рддреБрд▓рд╛ тЩО upto 24:51:38, рдЙрдкрд░рд╛рдиреНрдд: рд╡реГрд╢реНрдЪрд┐рдХ тЩП"}, {"title": "рджрд┐рдирдорд╛рди", "value": "32 рдШрдбреА 47 рдкрд▓рд╛ - 13hr 7min"}, {"title": "рдЛрддреБ", "value": "рд╡рд░реНрд╖рд╛-Monsoon"}, {"title": "рдЖрдпрд╛рди", "value": "рджрдХреНрд╖рд┐рдгрд╛рдпрди"}]