[{"title": "рд╡рд┐.рд╕рдВ", "value": "реирежреорем рдлрд╛рдЧреБрди рем рд╕реЛрдордмрд╛рд░"}, {"title": "рдИрд╕рд╡реА", "value": "2030 Feb 18, Monday"}, {"title": "рдиреЗрдкрд╛рд▓ рд╕рдВрд╡рдд", "value": "1150 рд╕рд┐рд▓реНрд▓рд╛рдереНрд╡ рдкреБрдиреНрд╣рд┐-15"}, {"title": "рд╕реВрд░реНрдп", "value": "6:40тШАя╕П, 17:58ЁЯМд"}, {"title": "рдЪрдиреНрджреНрд░", "value": "18:08тШ╜, 6:15тШ╛"}, {"title": "рддрд┐рдерд┐", "value": "рдкреВрд░реНрдгрд┐рдорд╛ upto 12:2:49, рдЙрдкрд░рд╛рдиреНрдд: рдкреНрд░рддрд┐рдкрджрд╛"}, {"title": "рдкрдХреНрд╖", "value": "рдорд╛рдШ рд╢реБрдХреНрд▓ рдкрдХреНрд╖ ЁЯМХ"}, {"title": "рдирдХреНрд╖рддреНрд░", "value": "рдордШрд╛ upto 25:50:2, рдЙрдкрд░рд╛рдиреНрдд: рдкреВрд░реНрд╡рдлрд╛рд▓реНрдЧреБрдиреА"}, {"title": "рдпреЛрдЧ", "value": "рдЕрддрд┐рдЧрдВрдб upto 27:0:47, рдЙрдкрд░рд╛рдиреНрдд: рд╕реБрдХрд░реНрдорд╛"}, {"title": "рдХрд░рдг", "value": "рдмрд╡ upto 12:2:49"}, {"title": "рдЪрдиреНрджреНрд░ рд░рд╛рд╢рд┐", "value": "рд╕рд┐рдВрд╣ тЩМ"}, {"title": "рджрд┐рдирдорд╛рди", "value": "28 рдШрдбреА 15 рдкрд▓рд╛ - 11hr 18min"}, {"title": "рдЛрддреБ", "value": "рд╢рд┐рд╢рд┐рд░-Winter"}, {"title": "рдЖрдпрд╛рди", "value": "рдЙрддреНрддрд░рд╛рдпрдг"}]