[{"title": "рд╡рд┐.рд╕рдВ", "value": "реирежренреп рдорд╛рдШ реирен рд╢реБрдХреНрд░рд╡рд╛рд░"}, {"title": "рдИрд╕рд╡реА", "value": "2023 Feb 10, Friday"}, {"title": "рдиреЗрдкрд╛рд▓ рд╕рдВрд╡рдд", "value": "1143 рд╕рд┐рд▓реНрд▓рд╛рдЧрд╛ рдЪрддреБрд░реНрдереА-19"}, {"title": "рд╕реВрд░реНрдп", "value": "6:46тШАя╕П, 17:52ЁЯМд"}, {"title": "рдЪрдиреНрджреНрд░", "value": "21:58тШ╜, 9:19тШ╛"}, {"title": "рддрд┐рдерд┐", "value": "рдЪрддреБрд░реНрдереА upto 8:13:52, рдЙрдкрд░рд╛рдиреНрдд: рдкрдЮреНрдЪрдореА"}, {"title": "рдкрдХреНрд╖", "value": "рдлрд╛рдЧреБрди рдХреГрд╖реНрдг рдкрдХреНрд╖ ЁЯМЦ"}, {"title": "рдирдХреНрд╖рддреНрд░", "value": "рд╣рд╕реНрдд upto 24:32:17, рдЙрдкрд░рд╛рдиреНрдд: рдЪрд┐рддреНрд░рд╛"}, {"title": "рдпреЛрдЧ", "value": "рдзреГрддрд┐ upto 16:58:2, рдЙрдкрд░рд╛рдиреНрдд: рд╢реВрд▓"}, {"title": "рдХрд░рдг", "value": "рдмрд╛рд▓рд╡ upto 8:13:52"}, {"title": "рдЪрдиреНрджреНрд░ рд░рд╛рд╢рд┐", "value": "рдХрдиреНрдпрд╛ тЩН"}, {"title": "рджрд┐рдирдорд╛рди", "value": "27 рдШрдбреА 45 рдкрд▓рд╛ - 11hr 6min"}, {"title": "рдЛрддреБ", "value": "рд╢рд┐рд╢рд┐рд░-Winter"}, {"title": "рдЖрдпрд╛рди", "value": "рдЙрддреНрддрд░рд╛рдпрдг"}]