[{"title": "рд╡рд┐.рд╕рдВ", "value": "реирежрепреж рдХрд╛рд░реНрддрд┐рдХ реиреи рд╕реЛрдордмрд╛рд░"}, {"title": "рдИрд╕рд╡реА", "value": "2033 Nov 7, Monday"}, {"title": "рдиреЗрдкрд╛рд▓ рд╕рдВрд╡рдд", "value": "1154 рдХрдЫрд▓рд╛рдЧрд╛ рдкрд╛рд░реБ-16"}, {"title": "рд╕реВрд░реНрдп", "value": "6:19тШАя╕П, 17:17ЁЯМд"}, {"title": "рдЪрдиреНрджреНрд░", "value": "17:57тШ╜, 6:33тШ╛"}, {"title": "рддрд┐рдерд┐", "value": "рдкреНрд░рддрд┐рдкрджрд╛ upto 22:50:45, рдЙрдкрд░рд╛рдиреНрдд: рджреНрд╡рд┐рддреАрдпрд╛"}, {"title": "рдкрдХреНрд╖", "value": "рдордВрд╕рд┐рд░ рдХреГрд╖реНрдг рдкрдХреНрд╖ ЁЯМЦ"}, {"title": "рдирдХреНрд╖рддреНрд░", "value": "рднрд░рдгреА upto 12:16:55, рдЙрдкрд░рд╛рдиреНрдд: рдХреГрддреНрддрд┐рдХрд╛"}, {"title": "рдпреЛрдЧ", "value": "рд╡реНрдпрддреАрдкрд╛рдд upto 11:2:13, рдЙрдкрд░рд╛рдиреНрдд: рд╡рд░рд┐рдпрд╛рди"}, {"title": "рдХрд░рдг", "value": "рдмрд╛рд▓рд╡ upto 12:33:46, рдЙрдкрд░рд╛рдиреНрдд: рдХреМрд▓рд╡ upto 22:50:45"}, {"title": "рдЪрдиреНрджреНрд░ рд░рд╛рд╢рд┐", "value": "рдореЗрд╖ тЩИ upto 17:36:47, рдЙрдкрд░рд╛рдиреНрдд: рд╡реГрд╖ тЩЙ"}, {"title": "рджрд┐рдирдорд╛рди", "value": "27 рдШрдбреА 25 рдкрд▓рд╛ - 10hr 58min"}, {"title": "рдЛрддреБ", "value": "рд╢рд░рджреН-Autumn"}, {"title": "рдЖрдпрд╛рди", "value": "рджрдХреНрд╖рд┐рдгрд╛рдпрди"}]