[{"title": "рд╡рд┐.рд╕рдВ", "value": "реирежренрео рдкреМрд╖ реирен рдордВрдЧрд▓рд╡рд╛рд░"}, {"title": "рдИрд╕рд╡реА", "value": "2022 Jan 11, Tuesday"}, {"title": "рдиреЗрдкрд╛рд▓ рд╕рдВрд╡рдд", "value": "1142 рдкреЛрд╣реЗрд▓рд╛рдереНрд╡ рдирд╡рдореА-9"}, {"title": "рд╕реВрд░реНрдп", "value": "6:57тШАя╕П, 17:28ЁЯМд"}, {"title": "рдЪрдиреНрджреНрд░", "value": "12:41тШ╜, 1:05тШ╛"}, {"title": "рддрд┐рдерд┐", "value": "рдирд╡рдореА upto 14:41:14, рдЙрдкрд░рд╛рдиреНрдд: рджрд╢рдореА"}, {"title": "рдкрдХреНрд╖", "value": "рдкреМрд╖ рд╢реБрдХреНрд▓ рдкрдХреНрд╖ ЁЯМУ"}, {"title": "рдирдХреНрд╖рддреНрд░", "value": "рдЕрд╢реНрд╡рд┐рдиреА upto 11:28:28, рдЙрдкрд░рд╛рдиреНрдд: рднрд░рдгреА"}, {"title": "рдпреЛрдЧ", "value": "рд╕рд┐рджреНрдз upto 11:13:43, рдЙрдкрд░рд╛рдиреНрдд: рд╕рд╛рдШреНрдп"}, {"title": "рдХрд░рдг", "value": "рдХреМрд▓рд╡ upto 14:41:14"}, {"title": "рдЪрдиреНрджреНрд░ рд░рд╛рд╢рд┐", "value": "рдореЗрд╖ тЩИ"}, {"title": "рджрд┐рдирдорд╛рди", "value": "26 рдШрдбреА 17 рдкрд▓рд╛ - 10hr 31min"}, {"title": "рдЛрддреБ", "value": "рд╣реЗрдордиреНрдд-Pre-winter"}, {"title": "рдЖрдпрд╛рди", "value": "рджрдХреНрд╖рд┐рдгрд╛рдпрди"}]