[{"title": "рд╡рд┐.рд╕рдВ", "value": "реирежреореи рдЪреИрддреНрд░ резреж рдордВрдЧрд▓рд╡рд╛рд░"}, {"title": "рдИрд╕рд╡реА", "value": "2026 Mar 24, Tuesday"}, {"title": "рдиреЗрдкрд╛рд▓ рд╕рдВрд╡рдд", "value": "1146 рдЪреМрд▓рд╛рдереНрд╡ рд╖рд╖реНрдареА-6"}, {"title": "рд╕реВрд░реНрдп", "value": "6:04тШАя╕П, 18:18ЁЯМд"}, {"title": "рдЪрдиреНрджреНрд░", "value": "9:30тШ╜, N/AтШ╛"}, {"title": "рддрд┐рдерд┐", "value": "рд╖рд╖реНрдареА upto 16:26:28, рдЙрдкрд░рд╛рдиреНрдд: рд╕рдкреНрддрдореА"}, {"title": "рдкрдХреНрд╖", "value": "рдЪреИрддреНрд░ рд╢реБрдХреНрд▓ рдкрдХреНрд╖ ЁЯМУ"}, {"title": "рдирдХреНрд╖рддреНрд░", "value": "рд░реЛрд╣рд┐рдгреА upto 19:22:57, рдЙрдкрд░рд╛рдиреНрдд: рдореГрдЧрд╢рд┐рд░рд╛"}, {"title": "рдпреЛрдЧ", "value": "рдкреНрд░реАрддрд┐ upto 9:24:23, рдЙрдкрд░рд╛рдиреНрдд: рдЖрдпреБрд╖реНрдорд╛рди"}, {"title": "рдХрд░рдг", "value": "рддреИрддрд┐рд▓ upto 16:26:28"}, {"title": "рдЪрдиреНрджреНрд░ рд░рд╛рд╢рд┐", "value": "рд╡реГрд╖ тЩЙ upto 30:33:10, рдЙрдкрд░рд╛рдиреНрдд: рдорд┐рдереБрди тЩК"}, {"title": "рджрд┐рдирдорд╛рди", "value": "30 рдШрдбреА 35 рдкрд▓рд╛ - 12hr 14min"}, {"title": "рдЛрддреБ", "value": "рд╡рд╕рдиреНрдд-Spring"}, {"title": "рдЖрдпрд╛рди", "value": "рдЙрддреНрддрд░рд╛рдпрдг"}]