[{"title": "рд╡рд┐.рд╕рдВ", "value": "реирежреорез рдордВрд╕рд┐рд░ реирен рдмрд┐рд╣реАрд╡рд╛рд░"}, {"title": "рдИрд╕рд╡реА", "value": "2024 Dec 12, Thursday"}, {"title": "рдиреЗрдкрд╛рд▓ рд╕рдВрд╡рдд", "value": "1145 рдерд┐рдВрд▓рд╛рдереНрд╡ рджреНрд╡рд╛рджрд╢реА-12"}, {"title": "рд╕реВрд░реНрдп", "value": "6:46тШАя╕П, 17:11ЁЯМд"}, {"title": "рдЪрдиреНрджреНрд░", "value": "14:34тШ╜, 3:24тШ╛"}, {"title": "рддрд┐рдерд┐", "value": "рджреНрд╡рд╛рджрд╢реА upto 22:42:21, рдЙрдкрд░рд╛рдиреНрдд: рддреНрд░рдпреЛрджрд╢реА"}, {"title": "рдкрдХреНрд╖", "value": "рдордВрд╕рд┐рд░ рд╢реБрдХреНрд▓ рдкрдХреНрд╖ ЁЯМФ"}, {"title": "рдирдХреНрд╖рддреНрд░", "value": "рдЕрд╢реНрд╡рд┐рдиреА upto 10:8:24, рдЙрдкрд░рд╛рдиреНрдд: рднрд░рдгреА"}, {"title": "рдпреЛрдЧ", "value": "рдкрд░рд┐рдШ upto 15:38:35, рдЙрдкрд░рд╛рдиреНрдд: рд╢рд┐рд╡"}, {"title": "рдХрд░рдг", "value": "рдмрд╡ upto 12:4:40, рдЙрдкрд░рд╛рдиреНрдд: рдмрд╛рд▓рд╡ upto 22:42:21"}, {"title": "рдЪрдиреНрджреНрд░ рд░рд╛рд╢рд┐", "value": "рдореЗрд╖ тЩИ"}, {"title": "рджрд┐рдирдорд╛рди", "value": "26 рдШрдбреА 2 рдкрд▓рд╛ - 10hr 25min"}, {"title": "рдЛрддреБ", "value": "рд╣реЗрдордиреНрдд-Pre-winter"}, {"title": "рдЖрдпрд╛рди", "value": "рджрдХреНрд╖рд┐рдгрд╛рдпрди"}]