[{"title": "рд╡рд┐.рд╕рдВ", "value": "реирежреорен рд╢реНрд░рд╛рд╡рди резрео рд╢рдирд┐рд╡рд╛рд░"}, {"title": "рдИрд╕рд╡реА", "value": "2030 Aug 3, Saturday"}, {"title": "рдиреЗрдкрд╛рд▓ рд╕рдВрд╡рдд", "value": "1150 рдЧреБрд▓рд╛рдереНрд╡ рдЪрддреБрд░реНрдереА-4"}, {"title": "рд╕реВрд░реНрдп", "value": "5:28тШАя╕П, 18:53ЁЯМд"}, {"title": "рдЪрдиреНрджреНрд░", "value": "8:55тШ╜, 21:03тШ╛"}, {"title": "рддрд┐рдерд┐", "value": "рдЪрддреБрд░реНрдереА upto 15:52:28, рдЙрдкрд░рд╛рдиреНрдд: рдкрдЮреНрдЪрдореА"}, {"title": "рдкрдХреНрд╖", "value": "рд╢реНрд░рд╛рд╡рди рд╢реБрдХреНрд▓ рдкрдХреНрд╖ ЁЯМТ"}, {"title": "рдирдХреНрд╖рддреНрд░", "value": "рдЙрддреНрддрд░рдлрд╛рд▓реНрдЧреБрдиреА upto 25:0:15, рдЙрдкрд░рд╛рдиреНрдд: рд╣рд╕реНрдд"}, {"title": "рдпреЛрдЧ", "value": "рд╢рд┐рд╡ upto 24:5:2, рдЙрдкрд░рд╛рдиреНрдд: рд╕рд┐рджреНрдз"}, {"title": "рдХрд░рдг", "value": "рд╡рд┐рд╖реНрдЯрд┐ upto 15:52:28"}, {"title": "рдЪрдиреНрджреНрд░ рд░рд╛рд╢рд┐", "value": "рд╕рд┐рдВрд╣ тЩМ upto 7:15:1, рдЙрдкрд░рд╛рдиреНрдд: рдХрдиреНрдпрд╛ тЩН"}, {"title": "рджрд┐рдирдорд╛рди", "value": "33 рдШрдбреА 32 рдкрд▓рд╛ - 13hr 25min"}, {"title": "рдЛрддреБ", "value": "рд╡рд░реНрд╖рд╛-Monsoon"}, {"title": "рдЖрдпрд╛рди", "value": "рджрдХреНрд╖рд┐рдгрд╛рдпрди"}]