[{"title": "рд╡рд┐.рд╕рдВ", "value": "реирежреорез рдЬреЗрд╖реНрда реирек рдмрд┐рд╣реАрд╡рд╛рд░"}, {"title": "рдИрд╕рд╡реА", "value": "2024 Jun 6, Thursday"}, {"title": "рдиреЗрдкрд╛рд▓ рд╕рдВрд╡рдд", "value": "1144 рд╡рдЫрд▓рд╛рдЧрд╛ рдЖрдореИ-30"}, {"title": "рд╕реВрд░реНрдп", "value": "5:08тШАя╕П, 18:58ЁЯМд"}, {"title": "рдЪрдиреНрджреНрд░", "value": "4:38тШ╜, 19:13тШ╛"}, {"title": "рддрд┐рдерд┐", "value": "рдФрдВрд╕реА upto 18:27:32, рдЙрдкрд░рд╛рдиреНрдд: рдкреНрд░рддрд┐рдкрджрд╛"}, {"title": "рдкрдХреНрд╖", "value": "рдЬреЗрд╖реНрда рдХреГрд╖реНрдг рдкрдХреНрд╖ ЁЯМС"}, {"title": "рдирдХреНрд╖рддреНрд░", "value": "рд░реЛрд╣рд┐рдгреА upto 20:36:11, рдЙрдкрд░рд╛рдиреНрдд: рдореГрдЧрд╢рд┐рд░рд╛"}, {"title": "рдпреЛрдЧ", "value": "рдзреГрддрд┐ upto 22:28:11, рдЙрдкрд░рд╛рдиреНрдд: рд╢реВрд▓"}, {"title": "рдХрд░рдг", "value": "рдЪрддреБрд╖реНрдкрд╛рдж upto 7:15:50, рдЙрдкрд░рд╛рдиреНрдд: рдирд╛рдЧ upto 18:27:32"}, {"title": "рдЪрдиреНрджреНрд░ рд░рд╛рд╢рд┐", "value": "рд╡реГрд╖ тЩЙ"}, {"title": "рджрд┐рдирдорд╛рди", "value": "34 рдШрдбреА 35 рдкрд▓рд╛ - 13hr 50min"}, {"title": "рдЛрддреБ", "value": "рдЧреНрд░реАрд╖реНрдо-Summer"}, {"title": "рдЖрдпрд╛рди", "value": "рдЙрддреНрддрд░рд╛рдпрдг"}]