[{"title": "рд╡рд┐.рд╕рдВ", "value": "реирежренрео рдЪреИрддреНрд░ рел рд╢рдирд┐рд╡рд╛рд░"}, {"title": "рдИрд╕рд╡реА", "value": "2022 Mar 19, Saturday"}, {"title": "рдиреЗрдкрд╛рд▓ рд╕рдВрд╡рдд", "value": "1142 рдЪрд┐рд▓реНрд▓рд╛рдЧрд╛ рдкрд╛рд░реБ-16"}, {"title": "рд╕реВрд░реНрдп", "value": "6:10тШАя╕П, 18:15ЁЯМд"}, {"title": "рдЪрдиреНрджреНрд░", "value": "19:17тШ╜, 6:49тШ╛"}, {"title": "рддрд┐рдерд┐", "value": "рдкреНрд░рддрд┐рдкрджрд╛ upto 11:51:44, рдЙрдкрд░рд╛рдиреНрдд: рджреНрд╡рд┐рддреАрдпрд╛"}, {"title": "рдкрдХреНрд╖", "value": "рдЪреИрддреНрд░ рдХреГрд╖реНрдг рдкрдХреНрд╖ ЁЯМЦ"}, {"title": "рдирдХреНрд╖рддреНрд░", "value": "рд╣рд╕реНрдд upto 23:52:32, рдЙрдкрд░рд╛рдиреНрдд: рдЪрд┐рддреНрд░рд╛"}, {"title": "рдпреЛрдЧ", "value": "рд╡реГрджреНрдзрд┐ upto 21:15:23, рдЙрдкрд░рд╛рдиреНрдд: рдШреНрд░реБрд╡"}, {"title": "рдХрд░рдг", "value": "рдХреМрд▓рд╡ upto 11:51:44"}, {"title": "рдЪрдиреНрджреНрд░ рд░рд╛рд╢рд┐", "value": "рдХрдиреНрдпрд╛ тЩН"}, {"title": "рджрд┐рдирдорд╛рди", "value": "30 рдШрдбреА 12 рдкрд▓рд╛ - 12hr 5min"}, {"title": "рдЛрддреБ", "value": "рд╡рд╕рдиреНрдд-Spring"}, {"title": "рдЖрдпрд╛рди", "value": "рдЙрддреНрддрд░рд╛рдпрдг"}]