[{"title": "рд╡рд┐.рд╕рдВ", "value": "реирежреорей рдордВрд╕рд┐рд░ рен рдЖрдЗрддрд╡рд╛рд░"}, {"title": "рдИрд╕рд╡реА", "value": "2026 Nov 22, Sunday"}, {"title": "рдиреЗрдкрд╛рд▓ рд╕рдВрд╡рдд", "value": "1147 рдХрдЫрд▓рд╛рдереНрд╡ рддреНрд░рдпреЛрджрд╢реА-13"}, {"title": "рд╕реВрд░реНрдп", "value": "6:31тШАя╕П, 17:10ЁЯМд"}, {"title": "рдЪрдиреНрджреНрд░", "value": "15:10тШ╜, 3:50тШ╛"}, {"title": "рддрд┐рдерд┐", "value": "рддреНрд░рдпреЛрджрд╢реА upto 26:51:16, рдЙрдкрд░рд╛рдиреНрдд: рдЪрддреБрд░реНрджрд╢реА"}, {"title": "рдкрдХреНрд╖", "value": "рдХрд╛рд░реНрддрд┐рдХ рд╢реБрдХреНрд▓ рдкрдХреНрд╖ ЁЯМФ"}, {"title": "рдирдХреНрд╖рддреНрд░", "value": "рдЕрд╢реНрд╡рд┐рдиреА upto 28:12:37, рдЙрдкрд░рд╛рдиреНрдд: рднрд░рдгреА"}, {"title": "рдпреЛрдЧ", "value": "рд╡реНрдпрддреАрдкрд╛рдд upto 23:41:40, рдЙрдкрд░рд╛рдиреНрдд: рд╡рд░рд┐рдпрд╛рди"}, {"title": "рдХрд░рдг", "value": "рдХреМрд▓рд╡ upto 16:2:29, рдЙрдкрд░рд╛рдиреНрдд: рддреИрддрд┐рд▓ upto 26:51:16"}, {"title": "рдЪрдиреНрджреНрд░ рд░рд╛рд╢рд┐", "value": "рдореАрди тЩУ upto 6:10:41, рдЙрдкрд░рд╛рдиреНрдд: рдореЗрд╖ тЩИ"}, {"title": "рджрд┐рдирдорд╛рди", "value": "26 рдШрдбреА 37 рдкрд▓рд╛ - 10hr 39min"}, {"title": "рдЛрддреБ", "value": "рд╣реЗрдордиреНрдд-Pre-winter"}, {"title": "рдЖрдпрд╛рди", "value": "рджрдХреНрд╖рд┐рдгрд╛рдпрди"}]