[{"title": "рд╡рд┐.рд╕рдВ", "value": "реирежреореж рдЬреЗрд╖реНрда рейреи рдмрд┐рд╣реАрд╡рд╛рд░"}, {"title": "рдИрд╕рд╡реА", "value": "2023 Jun 15, Thursday"}, {"title": "рдиреЗрдкрд╛рд▓ рд╕рдВрд╡рдд", "value": "1143 рддрдЫрд▓рд╛рдЧрд╛ рджреНрд╡рд╛рджрд╢реА-27"}, {"title": "рд╕реВрд░реНрдп", "value": "5:08тШАя╕П, 19:02ЁЯМд"}, {"title": "рдЪрдиреНрджреНрд░", "value": "2:48тШ╜, 16:35тШ╛"}, {"title": "рддрд┐рдерд┐", "value": "рджреНрд╡рд╛рджрд╢реА upto 8:50:15, рдЙрдкрд░рд╛рдиреНрдд: рддреНрд░рдпреЛрджрд╢реА"}, {"title": "рдкрдХреНрд╖", "value": "рдЖрд╖рд╛рдв рдХреГрд╖реНрдг рдкрдХреНрд╖ ЁЯМШ"}, {"title": "рдирдХреНрд╖рддреНрд░", "value": "рднрд░рдгреА upto 14:31:2, рдЙрдкрд░рд╛рдиреНрдд: рдХреГрддреНрддрд┐рдХрд╛"}, {"title": "рдпреЛрдЧ", "value": "рд╕реБрдХрд░реНрдорд╛ upto 26:20:5, рдЙрдкрд░рд╛рдиреНрдд: рдзреГрддрд┐"}, {"title": "рдХрд░рдг", "value": "рддреИрддрд┐рд▓ upto 8:50:15"}, {"title": "рдЪрдиреНрджреНрд░ рд░рд╛рд╢рд┐", "value": "рдореЗрд╖ тЩИ upto 20:42:39, рдЙрдкрд░рд╛рдиреНрдд: рд╡реГрд╖ тЩЙ"}, {"title": "рджрд┐рдирдорд╛рди", "value": "34 рдШрдбреА 45 рдкрд▓рд╛ - 13hr 54min"}, {"title": "рдЛрддреБ", "value": "рдЧреНрд░реАрд╖реНрдо-Summer"}, {"title": "рдЖрдпрд╛рди", "value": "рдЙрддреНрддрд░рд╛рдпрдг"}]