[{"title": "рд╡рд┐.рд╕рдВ", "value": "реирежренрео рдХрд╛рд░реНрддрд┐рдХ реирел рдмрд┐рд╣реАрд╡рд╛рд░"}, {"title": "рдИрд╕рд╡реА", "value": "2021 Nov 11, Thursday"}, {"title": "рдиреЗрдкрд╛рд▓ рд╕рдВрд╡рдд", "value": "1142 рдХрдЫрд▓рд╛рдереНрд╡ рд╕рдкреНрддрдореА-7"}, {"title": "рд╕реВрд░реНрдп", "value": "6:22тШАя╕П, 17:14ЁЯМд"}, {"title": "рдЪрдиреНрджреНрд░", "value": "12:43тШ╜, 23:37тШ╛"}, {"title": "рддрд┐рдерд┐", "value": "рд╕рдкреНрддрдореА upto 7:7:12, рдЙрдкрд░рд╛рдиреНрдд: рдЕрд╖реНрдЯрдореА upto 30:8:9"}, {"title": "рдкрдХреНрд╖", "value": "рдХрд╛рд░реНрддрд┐рдХ рд╢реБрдХреНрд▓ рдкрдХреНрд╖ ЁЯМУ"}, {"title": "рдирдХреНрд╖рддреНрд░", "value": "рд╢реНрд░рд╡рдг upto 15:20:13, рдЙрдкрд░рд╛рдиреНрдд: рдзрдирд┐рд╖реНрдард╛"}, {"title": "рдпреЛрдЧ", "value": "рдЧрдгреНрдб upto 7:0:1, рдЙрдкрд░рд╛рдиреНрдд: рд╡реГрджреНрдзрд┐ (рд╕рдорд╛рдкреНрддреА)"}, {"title": "рдХрд░рдг", "value": "рд╡рдгрд┐рдЬ upto 7:7:12"}, {"title": "рдЪрдиреНрджреНрд░ рд░рд╛рд╢рд┐", "value": "рдордХрд░ тЩС upto 27:10:3, рдЙрдкрд░рд╛рдиреНрдд: рдХреБрдореНрдн тЩТ"}, {"title": "рджрд┐рдирдорд╛рди", "value": "27 рдШрдбреА 10 рдкрд▓рд╛ - 10hr 52min"}, {"title": "рдЛрддреБ", "value": "рд╢рд░рджреН-Autumn"}, {"title": "рдЖрдпрд╛рди", "value": "рджрдХреНрд╖рд┐рдгрд╛рдпрди"}]