[{"title": "рд╡рд┐.рд╕рдВ", "value": "реирежреорео рдордВрд╕рд┐рд░ реирен рд╢рдирд┐рд╡рд╛рд░"}, {"title": "рдИрд╕рд╡реА", "value": "2031 Dec 13, Saturday"}, {"title": "рдиреЗрдкрд╛рд▓ рд╕рдВрд╡рдд", "value": "1152 рдХрдЫрд▓рд╛рдЧрд╛ рдЪрддреБрд░реНрджрд╢реА-29"}, {"title": "рд╕реВрд░реНрдп", "value": "6:46тШАя╕П, 17:11ЁЯМд"}, {"title": "рдЪрдиреНрджреНрд░", "value": "5:21тШ╜, 16:21тШ╛"}, {"title": "рддрд┐рдерд┐", "value": "рдЪрддреБрд░реНрджрд╢реА upto 17:44:41, рдЙрдкрд░рд╛рдиреНрдд: рдФрдВрд╕реА"}, {"title": "рдкрдХреНрд╖", "value": "рдордВрд╕рд┐рд░ рдХреГрд╖реНрдг рдкрдХреНрд╖ ЁЯМС"}, {"title": "рдирдХреНрд╖рддреНрд░", "value": "рдЕрдиреБрд░рд╛рдзрд╛ upto 20:33:21, рдЙрдкрд░рд╛рдиреНрдд: рдЬреНрдпреЗрд╖реНрдард╛"}, {"title": "рдпреЛрдЧ", "value": "рдзреГрддрд┐ upto 25:3:14, рдЙрдкрд░рд╛рдиреНрдд: рд╢реВрд▓"}, {"title": "рдХрд░рдг", "value": "рд╡рд┐рд╖реНрдЯрд┐(рднрджреНрд░рд╛) upto 7:6:43, рдЙрдкрд░рд╛рдиреНрдд: рд╢рдХреБрди upto 17:44:41"}, {"title": "рдЪрдиреНрджреНрд░ рд░рд╛рд╢рд┐", "value": "рд╡реГрд╢реНрдЪрд┐рдХ тЩП"}, {"title": "рджрд┐рдирдорд╛рди", "value": "26 рдШрдбреА 2 рдкрд▓рд╛ - 10hr 25min"}, {"title": "рдЛрддреБ", "value": "рд╣реЗрдордиреНрдд-Pre-winter"}, {"title": "рдЖрдпрд╛рди", "value": "рджрдХреНрд╖рд┐рдгрд╛рдпрди"}]